ExpressPigeon-0.0.8.dist-info/DESCRIPTION.rst
ExpressPigeon-0.0.8.dist-info/METADATA
ExpressPigeon-0.0.8.dist-info/RECORD
ExpressPigeon-0.0.8.dist-info/WHEEL
ExpressPigeon-0.0.8.dist-info/metadata.json
ExpressPigeon-0.0.8.dist-info/top_level.txt
expresspigeon/__init__.py
expresspigeon/autoresponders.py
expresspigeon/campaigns.py
expresspigeon/contacts.py
expresspigeon/dictionaries.py
expresspigeon/flows.py
expresspigeon/lists.py
expresspigeon/messages.py
expresspigeon/templates.py
