Metadata-Version: 2.0
Name: ExpressPigeon
Version: 0.0.8
Summary: ExpressPigeon API
Home-page: https://github.com/expresspigeon/expresspigeon-python
Author: Gleb Galkin
Author-email: gleb@expresspigeon.com
License: BSD
Keywords: expresspigeon api email marketing transactional
Platform: UNKNOWN
Classifier: Development Status :: 3 - Alpha
Classifier: Intended Audience :: Developers
Classifier: License :: OSI Approved :: BSD License
Classifier: Programming Language :: Python
Classifier: Topic :: Communications :: Email
Classifier: Topic :: Software Development :: Libraries
Classifier: Topic :: Software Development :: Libraries :: Python Modules
